counter/counter.v


module counter(out, clk, reset);

  parameter WIDTH = 8;

  output [WIDTH-1 : 0] out;
  input 	       clk, reset;

  reg [WIDTH-1 : 0]   out;
  wire 	       clk, reset;

  always @(posedge clk or posedge reset)
    if (reset)
      out <= 0;
    else
      out <= out + 1;

endmodule // counter

counter/tb_counter.v
module test;

  /* Make a regular pulsing clock. */
  reg clk = 0;
  wire [7:0] value;
  reg reset = 0;

  always #5 clk = !clk;

initial begin
    $display("hello counter");
    $monitor($time, "clk=%b, value=%b",clk,value);
       $dumpfile("counter.vcd");
       $dumpvars(0,c1);
       $dumpvars(0,test);
     #17 reset = 1;
     #11 reset = 0;
     #29 reset = 1;
     #11 reset = 0;
     #1000 $finish;
  end
  counter c1 (value, clk, reset);
endmodule // test

counter/counter.vcd
$date
	Sun Apr 11 11:03:16 2021
$end
$version
	Icarus Verilog
$end
$timescale
	1s
$end
$scope module test $end
$scope module c1 $end
$var wire 1 ! clk $end
$var wire 1 " reset $end
$var reg 8 # out [7:0] $end
$upscope $end
$upscope $end
$scope module test $end
$var wire 8 $ value [7:0] $end
$var reg 1 ! clk $end
$var reg 1 " reset $end
$scope module c1 $end
$upscope $end
$upscope $end
$enddefinitions $end
#0
$dumpvars
bx $
bx #
0"
0!
$end
#5
1!
#10
0!
#15
1!
#17
b0 #
b0 $
1"
#20
0!
#25
1!
#28
0"
#30
0!
#35
b1 #
b1 $
1!
#40
0!
#45
b10 #
b10 $
1!
#50
0!
#55
b11 #
b11 $
1!
#57
b0 #
b0 $
1"
#60
0!
#65
1!
#68
0"
#70
0!
#75
b1 #
b1 $
1!
#80
0!
#85
b10 #
b10 $
1!
#90
0!
#95
b11 #
b11 $
1!
#100
0!
#105
b100 #
b100 $
1!
#110
0!
#115
b101 #
b101 $
1!
#120
0!
#125
b110 #
b110 $
1!
#130
0!
#135
b111 #
b111 $
1!
#140
0!
#145
b1000 #
b1000 $
1!
#150
0!
#155
b1001 #
b1001 $
1!
#160
0!
#165
b1010 #
b1010 $
1!
#170
0!
#175
b1011 #
b1011 $
1!
#180
0!
#185
b1100 #
b1100 $
1!
#190
0!
#195
b1101 #
b1101 $
1!
#200
0!
#205
b1110 #
b1110 $
1!
#210
0!
#215
b1111 #
b1111 $
1!
#220
0!
#225
b10000 #
b10000 $
1!
#230
0!
#235
b10001 #
b10001 $
1!
#240
0!
#245
b10010 #
b10010 $
1!
#250
0!
#255
b10011 #
b10011 $
1!
#260
0!
#265
b10100 #
b10100 $
1!
#270
0!
#275
b10101 #
b10101 $
1!
#280
0!
#285
b10110 #
b10110 $
1!
#290
0!
#295
b10111 #
b10111 $
1!
#300
0!
#305
b11000 #
b11000 $
1!
#310
0!
#315
b11001 #
b11001 $
1!
#320
0!
#325
b11010 #
b11010 $
1!
#330
0!
#335
b11011 #
b11011 $
1!
#340
0!
#345
b11100 #
b11100 $
1!
#350
0!
#355
b11101 #
b11101 $
1!
#360
0!
#365
b11110 #
b11110 $
1!
#370
0!
#375
b11111 #
b11111 $
1!
#380
0!
#385
b100000 #
b100000 $
1!
#390
0!
#395
b100001 #
b100001 $
1!
#400
0!
#405
b100010 #
b100010 $
1!
#410
0!
#415
b100011 #
b100011 $
1!
#420
0!
#425
b100100 #
b100100 $
1!
#430
0!
#435
b100101 #
b100101 $
1!
#440
0!
#445
b100110 #
b100110 $
1!
#450
0!
#455
b100111 #
b100111 $
1!
#460
0!
#465
b101000 #
b101000 $
1!
#470
0!
#475
b101001 #
b101001 $
1!
#480
0!
#485
b101010 #
b101010 $
1!
#490
0!
#495
b101011 #
b101011 $
1!
#500
0!
#505
b101100 #
b101100 $
1!
#510
0!
#515
b101101 #
b101101 $
1!
#520
0!
#525
b101110 #
b101110 $
1!
#530
0!
#535
b101111 #
b101111 $
1!
#540
0!
#545
b110000 #
b110000 $
1!
#550
0!
#555
b110001 #
b110001 $
1!
#560
0!
#565
b110010 #
b110010 $
1!
#570
0!
#575
b110011 #
b110011 $
1!
#580
0!
#585
b110100 #
b110100 $
1!
#590
0!
#595
b110101 #
b110101 $
1!
#600
0!
#605
b110110 #
b110110 $
1!
#610
0!
#615
b110111 #
b110111 $
1!
#620
0!
#625
b111000 #
b111000 $
1!
#630
0!
#635
b111001 #
b111001 $
1!
#640
0!
#645
b111010 #
b111010 $
1!
#650
0!
#655
b111011 #
b111011 $
1!
#660
0!
#665
b111100 #
b111100 $
1!
#670
0!
#675
b111101 #
b111101 $
1!
#680
0!
#685
b111110 #
b111110 $
1!
#690
0!
#695
b111111 #
b111111 $
1!
#700
0!
#705
b1000000 #
b1000000 $
1!
#710
0!
#715
b1000001 #
b1000001 $
1!
#720
0!
#725
b1000010 #
b1000010 $
1!
#730
0!
#735
b1000011 #
b1000011 $
1!
#740
0!
#745
b1000100 #
b1000100 $
1!
#750
0!
#755
b1000101 #
b1000101 $
1!
#760
0!
#765
b1000110 #
b1000110 $
1!
#770
0!
#775
b1000111 #
b1000111 $
1!
#780
0!
#785
b1001000 #
b1001000 $
1!
#790
0!
#795
b1001001 #
b1001001 $
1!
#800
0!
#805
b1001010 #
b1001010 $
1!
#810
0!
#815
b1001011 #
b1001011 $
1!
#820
0!
#825
b1001100 #
b1001100 $
1!
#830
0!
#835
b1001101 #
b1001101 $
1!
#840
0!
#845
b1001110 #
b1001110 $
1!
#850
0!
#855
b1001111 #
b1001111 $
1!
#860
0!
#865
b1010000 #
b1010000 $
1!
#870
0!
#875
b1010001 #
b1010001 $
1!
#880
0!
#885
b1010010 #
b1010010 $
1!
#890
0!
#895
b1010011 #
b1010011 $
1!
#900
0!
#905
b1010100 #
b1010100 $
1!
#910
0!
#915
b1010101 #
b1010101 $
1!
#920
0!
#925
b1010110 #
b1010110 $
1!
#930
0!
#935
b1010111 #
b1010111 $
1!
#940
0!
#945
b1011000 #
b1011000 $
1!
#950
0!
#955
b1011001 #
b1011001 $
1!
#960
0!
#965
b1011010 #
b1011010 $
1!
#970
0!
#975
b1011011 #
b1011011 $
1!
#980
0!
#985
b1011100 #
b1011100 $
1!
#990
0!
#995
b1011101 #
b1011101 $
1!
#1000
0!
#1005
b1011110 #
b1011110 $
1!
#1010
0!
#1015
b1011111 #
b1011111 $
1!
#1020
0!
#1025
b1100000 #
b1100000 $
1!
#1030
0!
#1035
b1100001 #
b1100001 $
1!
#1040
0!
#1045
b1100010 #
b1100010 $
1!
#1050
0!
#1055
b1100011 #
b1100011 $
1!
#1060
0!
#1065
b1100100 #
b1100100 $
1!
